joke/__init__.py
joke/__main__.py
joke/eggs.py
joke/facts.py
joke/jokes.py
joke/quotes.py
axju_jokes-1.0.3.dist-info/LICENSE
axju_jokes-1.0.3.dist-info/METADATA
axju_jokes-1.0.3.dist-info/WHEEL
axju_jokes-1.0.3.dist-info/entry_points.txt
axju_jokes-1.0.3.dist-info/top_level.txt
axju_jokes-1.0.3.dist-info/RECORD
