Metadata-Version: 1.1
Name: axju-jokes
Version: 1.0.3
Summary: Jokes for python
Home-page: https://github.com/axju/joke
Author: Axel Juraske
Author-email: axel.juraske@short-report.de
License: MIT
Keywords: joke,fun,funny,api
Platform: UNKNOWN
Classifier: License :: OSI Approved :: MIT License
Classifier: Programming Language :: Python :: 3
Classifier: Programming Language :: Python :: 3.5
Classifier: Programming Language :: Python :: 3.6
Classifier: Programming Language :: Python :: 3.7
Classifier: Programming Language :: Python :: 3.8
Classifier: Programming Language :: Python :: 3 :: Only
Classifier: Topic :: Games/Entertainment
Classifier: Topic :: Internet
Classifier: Environment :: Console
